Metadata-Version: 2.0
Name: Pylons
Version: 1.0.3
Summary: Pylons Web Framework
Home-page: https://github.com/Pylons/pylons
Author: Ben Bangert, Philip Jenvey, James Gardner
Author-email: ben@groovie.org, pjenvey@underboss.org
License: BSD
Keywords: web wsgi lightweight framework sqlalchemy formencode mako templates
Platform: UNKNOWN
Classifier: Development Status :: 5 - Production/Stable
Classifier: Intended Audience :: Developers
Classifier: License :: OSI Approved :: BSD License
Classifier: Framework :: Pylons
Classifier: Programming Language :: Python
Classifier: Programming Language :: Python :: 2 :: Only
Classifier: Topic :: Internet :: WWW/HTTP
Classifier: Topic :: Internet :: WWW/HTTP :: Dynamic Content
Classifier: Topic :: Internet :: WWW/HTTP :: WSGI
Classifier: Topic :: Software Development :: Libraries :: Python Modules
Requires-Dist: Routes (>=1.12.3)
Requires-Dist: WebHelpers (>=0.6.4)
Requires-Dist: Beaker (>=1.5.4)
Requires-Dist: Paste (>=1.7.5.1)
Requires-Dist: PasteDeploy (>=1.5.0)
Requires-Dist: PasteScript (>=1.7.4.2)
Requires-Dist: FormEncode (>=1.2.4)
Requires-Dist: simplejson (>=2.2.1)
Requires-Dist: decorator (>=3.3.2)
Requires-Dist: nose (>=1.1.2)
Requires-Dist: Mako (>=0.5.0)
Requires-Dist: WebError (>=0.10.3)
Requires-Dist: WebTest (>=1.3.1)
Requires-Dist: Tempita (>=0.5.1)
Requires-Dist: MarkupSafe (>=0.15)
Requires-Dist: WebOb (>=1.1.1)
Provides-Extra: genshi
Requires-Dist: Genshi (>=0.6); extra == 'genshi'
Provides-Extra: jinja2
Requires-Dist: Jinja2; extra == 'jinja2'
